rag_palm/__init__.py
rag_palm/palm2Rag.py
dlrag_dev-0.0.6.dist-info/Licenses.txt
dlrag_dev-0.0.6.dist-info/METADATA
dlrag_dev-0.0.6.dist-info/WHEEL
dlrag_dev-0.0.6.dist-info/top_level.txt
dlrag_dev-0.0.6.dist-info/RECORD
